{
    "Plugins": [
        {
            "Info": {
                "Types": {
                    "HdNSIRendererPlugin": {
                        "bases": ["HdRendererPlugin"],
                        "displayName": "3Delight",
                        "priority": 99
                    },
                    "HdNSIDiscoveryPlugin": {
                        "bases": ["NdrDiscoveryPlugin"],
                        "displayName": "NSI osl Discovery"
                    },
                    "HdNSIOsoParserPlugin": {
                        "bases": ["NdrParserPlugin"],
                        "displayName": "NSI osl Parser"
                    },
                    "HdNSIAccelerationBlurPlugin": {
                        "bases": ["HdSceneIndexPlugin"],
                        "priority": 0,
                        "displayName": "NSI Acceleration blur"
                    }
                }
            },
            "LibraryPath": "@PLUG_INFO_LIBRARY_PATH@",
            "Name": "hdNSI",
            "ResourcePath": "@PLUG_INFO_RESOURCE_PATH@",
            "Root": "@PLUG_INFO_ROOT@",
            "Type": "library"
        }
    ]
}
